warmahordes_opendata/__init__.py
warmahordes_opendata/base.py
warmahordes_opendata/i18n.py
warmahordes_opendata/models.py
warmahordes_opendata/rules.py
warmahordes_opendata/themes.py
warmahordes_opendata/cli/__init__.py
warmahordes_opendata/cli/extract_messages.py
warmahordes_opendata/cli/models.py
warmahordes_opendata/cli/rules.py
warmahordes_opendata/cli/themes.py
warmahordes_opendata/data/model_aliases.yaml
warmahordes_opendata/data/models/circle/engine_structure/celestial_fulcrum.yaml
warmahordes_opendata/data/models/circle/engine_structure/well_of_orboros.yaml
warmahordes_opendata/data/models/circle/solo/blackclad_stoneshaper.yaml
warmahordes_opendata/data/models/circle/solo/blackclad_wayfarer.yaml
warmahordes_opendata/data/models/circle/solo/bloodweaver_night_witch.yaml
warmahordes_opendata/data/models/circle/solo/chuck_dogwood.yaml
warmahordes_opendata/data/models/circle/solo/druid_wilder.yaml
warmahordes_opendata/data/models/circle/solo/gallows_grove.yaml
warmahordes_opendata/data/models/circle/solo/krueger_the_stormseer.yaml
warmahordes_opendata/data/models/circle/solo/lord_of_the_feast.yaml
warmahordes_opendata/data/models/circle/solo/reeve_hunter.yaml
warmahordes_opendata/data/models/circle/solo/shivers.yaml
warmahordes_opendata/data/models/circle/solo/tharn_blood_shaman.yaml
warmahordes_opendata/data/models/circle/solo/tharn_ravager_shaman.yaml
warmahordes_opendata/data/models/circle/solo/tharn_ravager_white_mane.yaml
warmahordes_opendata/data/models/circle/solo/tharn_wolf_rider_champion.yaml
warmahordes_opendata/data/models/circle/solo/una_the_falconer.yaml
warmahordes_opendata/data/models/circle/solo/war_wolf.yaml
warmahordes_opendata/data/models/circle/solo/wolf_lord_morraig.yaml
warmahordes_opendata/data/models/circle/unit/brighid_and_caul.yaml
warmahordes_opendata/data/models/circle/unit/death_wolves.yaml
warmahordes_opendata/data/models/circle/unit/druid_mist_riders.yaml
warmahordes_opendata/data/models/circle/unit/druid_of_orboros_overseer.yaml
warmahordes_opendata-0.3.6.dist-info/AUTHORS
warmahordes_opendata-0.3.6.dist-info/LICENSE
warmahordes_opendata-0.3.6.dist-info/METADATA
warmahordes_opendata-0.3.6.dist-info/WHEEL
warmahordes_opendata-0.3.6.dist-info/entry_points.txt
warmahordes_opendata-0.3.6.dist-info/top_level.txt
warmahordes_opendata-0.3.6.dist-info/RECORD
