Metadata-Version: 2.1
Name: warmahordes-opendata
Version: 0.3.6
Summary: WARMACHINE® and HORDES® Open Data
Home-page: https://ironcodex.net/warmahordes_opendata
Author: Moisés Guimarães
Author-email: guimaraes@pm.me
License: UNKNOWN
Platform: UNKNOWN
Classifier: Intended Audience :: Developers
Classifier: License :: OSI Approved :: Apache Software License
Classifier: Operating System :: OS Independent
Classifier: Programming Language :: Python
Classifier: Programming Language :: Python :: 3
Classifier: Programming Language :: Python :: 3.9
Classifier: Programming Language :: Python :: 3 :: Only
Classifier: Programming Language :: Python :: Implementation :: CPython
Classifier: Topic :: Games/Entertainment
Classifier: Topic :: Games/Entertainment :: Board Games
Requires-Python: >=3.9
License-File: LICENSE
License-File: AUTHORS
Requires-Dist: oslo.i18n (>=5.0.1)
Requires-Dist: python-slugify (>=4.0.1)
Requires-Dist: PyYAML (>=5.4.1)
